whisperx/SubtitlesProcessor.pyi
whisperx/__init__.pyi
whisperx/alignment.pyi
whisperx/asr.pyi
whisperx/audio.pyi
whisperx/conjunctions.pyi
whisperx/diarize.pyi
whisperx/transcribe.pyi
whisperx/types.pyi
whisperx/utils.pyi
whisperx_stubs-3.4.6.dist-info/METADATA
whisperx_stubs-3.4.6.dist-info/WHEEL
whisperx_stubs-3.4.6.dist-info/top_level.txt
whisperx_stubs-3.4.6.dist-info/RECORD
