Metadata-Version: 2.4
Name: whisperx-stubs
Version: 3.4.6
Summary: Type stubs for whisperx
Author-email: Auto-generated <stub-generator@example.com>
License: MIT
Classifier: Development Status :: 4 - Beta
Classifier: Intended Audience :: Developers
Classifier: License :: OSI Approved :: MIT License
Classifier: Programming Language :: Python :: 3
Classifier: Programming Language :: Python :: 3.10
Classifier: Programming Language :: Python :: 3.11
Classifier: Programming Language :: Python :: 3.12
Classifier: Typing :: Stubs Only
Requires-Python: >=3.10
Requires-Dist: whisperx-typed>=3.4.5
